MANIFEST.in
README.rst
setup.py
django_eloqua.egg-info/PKG-INFO
django_eloqua.egg-info/SOURCES.txt
django_eloqua.egg-info/dependency_links.txt
django_eloqua.egg-info/requires.txt
django_eloqua.egg-info/top_level.txt
eloqua/__init__.py
eloqua/__init__.pyc
eloqua/clients.py
eloqua/clients.pyc
eloqua/exceptions.py
eloqua/exceptions.pyc
eloqua/lib.pyc
eloqua/models.py
eloqua/models.pyc
eloqua/settings.py
eloqua/settings.pyc
eloqua/urls.py
eloqua/urls.pyc
eloqua/views.py
eloqua/views.pyc
eloqua/management/__init__.py
eloqua/management/__init__.pyc
eloqua/management/commands/__init__.py
eloqua/management/commands/__init__.pyc
eloqua/management/commands/send_mail_from_url.py
eloqua/management/commands/send_mail_from_url.pyc
eloqua/migrations/0001_initial.py
eloqua/migrations/0001_initial.pyc
eloqua/migrations/0002_auto__chg_field_contact_contact_id.py
eloqua/migrations/0002_auto__chg_field_contact_contact_id.pyc
eloqua/migrations/0003_auto__add_field_contact_updated_at__add_field_contact_data.py
eloqua/migrations/0003_auto__add_field_contact_updated_at__add_field_contact_data.pyc
eloqua/migrations/__init__.py
eloqua/migrations/__init__.pyc
eloqua/templates/eloqua/landing_page.html